blackbelt/__init__.py
blackbelt/circle.py
blackbelt/config.py
blackbelt/configure.py
blackbelt/dependencies.py
blackbelt/deployment.py
blackbelt/errors.py
blackbelt/git.py
blackbelt/handle_github.py
blackbelt/handle_trello.py
blackbelt/messages.py
blackbelt/notify.py
blackbelt/slack.py
blackbelt/tasks.py
blackbelt/version.py
blackbelt/apis/__init__.py
blackbelt/apis/trello.py
blackbelt/commands/__init__.py
blackbelt/commands/dep.py
blackbelt/commands/gh.py
blackbelt/commands/init.py
blackbelt/commands/production.py
blackbelt/commands/rollback.py
blackbelt/commands/slack.py
blackbelt/commands/stage.py
blackbelt/commands/t.py
blackbelt/commands/version.py
blackbelt-0.16.0.data/scripts/bb
blackbelt-0.16.0.dist-info/METADATA
blackbelt-0.16.0.dist-info/RECORD
blackbelt-0.16.0.dist-info/WHEEL
blackbelt-0.16.0.dist-info/top_level.txt
