Metadata-Version: 2.1
Name: blackbelt
Version: 0.16.0
Summary: Project automation the Apiary way
Home-page: http://github.com/apiaryio/black-belt
Author: Lukas Linhart
Author-email: lukas@apiary.io
License: MIT
Platform: UNKNOWN
Classifier: Intended Audience :: Developers
Classifier: License :: OSI Approved :: MIT License
Classifier: Operating System :: OS Independent
Classifier: Programming Language :: Python
Classifier: Programming Language :: Python :: 2
Classifier: Programming Language :: Python :: 2.7
Classifier: Programming Language :: Python :: 3
Classifier: Programming Language :: Python :: 3.6
Classifier: Programming Language :: Python :: Implementation :: CPython
Classifier: Environment :: Console
Classifier: Topic :: Documentation
Classifier: Topic :: Utilities
Classifier: Topic :: Software Development :: Build Tools
Requires-Dist: six
Requires-Dist: click
Requires-Dist: requests
Requires-Dist: PyGithub
Requires-Dist: slacker (>=0.6.2)
Requires-Dist: pyopenssl
Requires-Dist: ndg-httpsclient
Requires-Dist: pyasn1
Requires-Dist: twine
